[
        {
            "id":1,
            "nombre":"Salame Colonial",
            "Category":"Fiambres",
            "NumPuesto":"",
            "NamePuesto":"Aldo Ferrero",
            "Precio":"500",
            "PrecioXKg":"",
            "SmallDescription":"Salame tipo colonial picado grueso",
            "img":"/public/img/pngSalame.png"
        },{
            "id":2,
            "nombre":"Salame Colonial",
            "Category":"Fiambres",
            "NumPuesto":"",
            "NamePuesto":"La esquina del Mercado ",
            "Precio":"500",
            "PrecioXKg":"",
            "SmallDescription":"Salame tipo colonial picado fino",
            "img":"/assets/img/pngSalame.png"
        },{
            "id":3,
            "nombre":"Queso Pategras",
            "Category":"Quesos",
            "NumPuesto":"",
            "NamePuesto":"El Polaco",
            "Precio":"500",
            "PrecioXKg":"",
            "SmallDescription":"Queso para acompañar un buen vino",
            "img":"pngPategras.png"
        },{
            "id":4,
            "nombre":"Queso Reggianito",
            "Category":"Quesos",
            "NumPuesto":"",
            "NamePuesto":"El Polaco",
            "Precio":"500",
            "PrecioXKg":"",
            "SmallDescription":"Queso para",
            "img":"pngReggianito.png"
        },{
            "id":5,
            "nombre":"Queso Senda",
            "Category":"Quesos",
            "NumPuesto":"",
            "NamePuesto":"El Polaco",
            "Precio":"500",
            "PrecioXKg":"",
            "SmallDescription":"Queso Senda cortado a maquina.  ",
            "img":"pngSenda.png"
        },{
            "id":6,
            "nombre":"Coca Cola",
            "Category":"Bebidas",
            "NumPuesto":"",
            "NamePuesto":"",
            "Precio":"500",
            "PrecioXKg":"",
            "SmallDescription":"",
            "img":"pngCocaCola.png"
        },{
            "id":7,
            "nombre":"Fanta",
            "Category":"Bebidas",
            "NumPuesto":"",
            "NamePuesto":"",
            "Precio":"500",
            "PrecioXKg":"",
            "SmallDescription":"Gaseosa sabor naranja",
            "img":"pngFanta.png"
        },{
            "id":8,
            "nombre":"Pepsi",
            "Category":"Bebidas",
            "NumPuesto":"",
            "NamePuesto":"",
            "Precio":"500",
            "PrecioXKg":"",
            "SmallDescription":"",
            "img":"pngPepsi"
        },{
            "id":9,
            "nombre":"Pritty",
            "Category":"Bebidas",
            "NumPuesto":"",
            "NamePuesto":"",
            "Precio":"500",
            "PrecioXKg":"",
            "SmallDescription":"Gaseosa sabor limon",
            "img":"pngPritty.png"
        },{
            "id":10,
            "nombre":"Sprite",
            "Category":"Bebidas",
            "NumPuesto":"",
            "NamePuesto":"",
            "Precio":"500",
            "PrecioXKg":"Gaseosa sabor limon",
            "SmallDescription":"",
            "img":"pngSprite.png"
        }
        
                ]
